{"replisome_trimers": {"CPLX0-2361[c]": -12, "CPLX0-3761[c]": -12}, "replisome_monomers": {"CPLX0-3621[c]": -4, "EG10239-MONOMER[c]": -4, "EG11500-MONOMER[c]": -4, "EG11412-MONOMER[c]": -4}, "active_replisomes": {"_add": [{"key": "dd0eeb06-e2f2-11eb-b85e-1e00312eb299", "state": {"coordinates": 0, "right_replichore": true, "domain_index": 1}}, {"key": "dd0eeb4c-e2f2-11eb-b85e-1e00312eb299", "state": {"coordinates": 0, "right_replichore": false, "domain_index": 1}}, {"key": "dd0eeb74-e2f2-11eb-b85e-1e00312eb299", "state": {"coordinates": 0, "right_replichore": true, "domain_index": 2}}, {"key": "dd0eeb9c-e2f2-11eb-b85e-1e00312eb299", "state": {"coordinates": 0, "right_replichore": false, "domain_index": 2}}]}, "listeners": {"replication_data": {"criticalMassPerOriC": 1.0003599459773012, "criticalInitiationMass": 975.0}}, "oriCs": {"_add": [{"key": "dd0ee782-e2f2-11eb-b85e-1e00312eb299", "state": {"domain_index": 3}}, {"key": "dd0ee89a-e2f2-11eb-b85e-1e00312eb299", "state": {"domain_index": 4}}], "_delete": [[1], [2]]}, "chromosome_domains": {"_add": [{"key": "dd0eec96-e2f2-11eb-b85e-1e00312eb299", "state": {"domain_index": 3, "child_domains": [-1, -1]}}, {"key": "dd0eed22-e2f2-11eb-b85e-1e00312eb299", "state": {"domain_index": 4, "child_domains": [-1, -1]}}, {"key": "dd0eed5e-e2f2-11eb-b85e-1e00312eb299", "state": {"domain_index": 5, "child_domains": [-1, -1]}}, {"key": "dd0eed90-e2f2-11eb-b85e-1e00312eb299", "state": {"domain_index": 6, "child_domains": [-1, -1]}}], "3": {"child_domains": [1, 2]}, "4": {"child_domains": [3, 4]}, "5": {"child_domains": [5, 6]}}}